test_valkey_glide_async-0.1.2.dist-info/METADATA
test_valkey_glide_async-0.1.2.dist-info/WHEEL
glide/__init__.py
glide/routes.py
glide/commands/__init__.py
glide/commands/server_modules/ft_options/ft_search_options.py
glide/commands/server_modules/ft_options/ft_create_options.py
glide/commands/server_modules/ft_options/ft_aggregate_options.py
glide/commands/server_modules/ft_options/ft_profile_options.py
glide/commands/server_modules/ft_options/ft_constants.py
glide/commands/server_modules/ft.py
glide/commands/server_modules/json_batch.py
glide/commands/server_modules/glide_json.py
glide/commands/command_args.py
glide/commands/stream.py
glide/commands/sorted_set.py
glide/commands/batch.py
glide/commands/async_commands/__init__.py
glide/commands/async_commands/standalone_commands.py
glide/commands/async_commands/core.py
glide/commands/async_commands/cluster_commands.py
glide/commands/core_options.py
glide/commands/bitmap.py
glide/protobuf/connection_request_pb2.py
glide/protobuf/connection_request_pb2.pyi
glide/protobuf/command_request_pb2.pyi
glide/protobuf/command_request_pb2.py
glide/protobuf/response_pb2.pyi
glide/protobuf/response_pb2.py
glide/constants.py
glide/exceptions.py
glide/py.typed
glide/glide_async/pyproject.toml
glide/glide_async/__init__.py
glide/glide_async/glide.pyi
glide/glide_async/Cargo.toml
glide/glide_async/glide_client.py
glide/protobuf_codec.py
glide/logger.py
glide/config.py
glide/glide.cpython-312-x86_64-linux-gnu.so
test_valkey_glide_async-0.1.2.dist-info/RECORD
